muses_bbcode/__init__.py
muses_bbcode/br_bbcode_tag.py
muses_bbcode/email_bbcode_tag.py
muses_bbcode/hr_bbcode_tag.py
muses_bbcode/invisible_bbcode_tag.py
muses_bbcode/justifier_bbcode_tag.py
muses_bbcode/mp3_bbcode_tag.py
muses_bbcode/preformatted_bbcode_tag.py
muses_bbcode/right_bbcode_tag.py
muses_bbcode-0.1.1600119741.dist-info/METADATA
muses_bbcode-0.1.1600119741.dist-info/WHEEL
muses_bbcode-0.1.1600119741.dist-info/top_level.txt
muses_bbcode-0.1.1600119741.dist-info/RECORD
