Metadata-Version: 2.1
Name: muses-bbcode
Version: 0.1.1600119741
Summary: Muses BBCodes
Home-page: UNKNOWN
Author: Eric Laugier
Author-email: eric.laugier@egen.guru
License: GNU Lesser General Public License v3 (LGPLv3)
Platform: UNKNOWN
Classifier: Development Status :: 3 - Alpha
Classifier: License :: OSI Approved :: GNU Lesser General Public License v3 (LGPLv3)
Classifier: Operating System :: OS Independent
Classifier: Programming Language :: Python
Classifier: Programming Language :: Python :: 3
Classifier: Programming Language :: Python :: 3 :: Only
Classifier: Programming Language :: Python :: 3.6
Classifier: Programming Language :: Python :: 3.7
Classifier: Programming Language :: Python :: 3.8
Classifier: Topic :: Software Development :: Libraries
Requires-Dist: django-precise-bbcode
